simplicial_operators/__init__.py
simplicial_operators/_utils.py
simplicial_operators/aw_ez_shih.py
simplicial_operators/barratt_eccles.py
simplicial_operators/base_class.py
simplicial_operators/cartan.py
simplicial_operators/steenrod.py
simplicial_operators/surjections.py
simplicial_operators-0.3.1.dist-info/METADATA
simplicial_operators-0.3.1.dist-info/WHEEL
simplicial_operators-0.3.1.dist-info/top_level.txt
simplicial_operators-0.3.1.dist-info/RECORD
