Metadata-Version: 2.1
Name: simplicial-operators
Version: 0.3.1
Summary: A package to define and use simplicial operators
Home-page: https://github.com/ammedmar/simplicial_operators
Author: Anibal M. Medina-Mardones
Author-email: anibal.medinamardones@epfl.ch
License: MIT
Platform: UNKNOWN
